tinycoder/__init__.py
tinycoder/app.py
tinycoder/app_builder.py
tinycoder/chat_history.py
tinycoder/code_applier.py
tinycoder/command_handler.py
tinycoder/config.py
tinycoder/context_manager.py
tinycoder/coverage_tool.py
tinycoder/docker_automation.py
tinycoder/docker_manager.py
tinycoder/edit_parser.py
tinycoder/file_manager.py
tinycoder/git_manager.py
tinycoder/input_preprocessor.py
tinycoder/llm_response_processor.py
tinycoder/local_import.py
tinycoder/notebook_converter.py
tinycoder/preferences.py
tinycoder/prompt_builder.py
tinycoder/prompts.py
tinycoder/repo_map.py
tinycoder/rule_manager.py
tinycoder/shell_executor.py
tinycoder/test_docker_manager.py
tinycoder/test_edit_parser.py
tinycoder/test_git_manager.py
tinycoder/test_integration.py
tinycoder/test_notebook_converter.py
tinycoder/test_prompt_builder.py
tinycoder/test_repo_map.py
tinycoder/test_shell_executor.py
tinycoder/unittest_runner.py
tinycoder/linters/__init__.py
tinycoder/linters/css_validator.py
tinycoder/linters/html_linter.py
tinycoder/linters/python_linter.py
tinycoder/linters/test_css_validator.py
tinycoder/linters/test_html_linter.py
tinycoder/linters/test_python_linter.py
tinycoder/rules/__init__.py
tinycoder/rules/foundation_css_with_vanilla_js.md
tinycoder/rules/llm_prompting_guide.md
tinycoder/rules/python_logging.md
tinycoder/rules/python_security.md
tinycoder/rules/python_style_guide.md
tinycoder/rules/python_unittest_best_practices.md
tinycoder/rules/web_accessibility_a11y_guide.md
tinycoder/ui/__init__.py
tinycoder/ui/app_formatter.py
tinycoder/ui/command_completer.py
tinycoder/ui/console_interface.py
tinycoder/ui/log_formatter.py
tinycoder/ui/markdown_formatter.py
tinycoder/ui/session_summary.py
tinycoder/ui/spinner.py
tinycoder-0.8.6.dist-info/licenses/LICENSE
tinycoder-0.8.6.dist-info/METADATA
tinycoder-0.8.6.dist-info/WHEEL
tinycoder-0.8.6.dist-info/entry_points.txt
tinycoder-0.8.6.dist-info/top_level.txt
tinycoder-0.8.6.dist-info/RECORD
